cr_cube-3.1.5-py3.11-nspkg.pth
cr/cube/__init__.py
cr/cube/collator.py
cr/cube/cube.py
cr/cube/cubepart.py
cr/cube/dimension.py
cr/cube/enums.py
cr/cube/min_base_size_mask.py
cr/cube/scalar.py
cr/cube/smoothing.py
cr/cube/util.py
cr/cube/matrix/__init__.py
cr/cube/matrix/assembler.py
cr/cube/matrix/cubemeasure.py
cr/cube/matrix/measure.py
cr/cube/matrix/subtotals.py
cr/cube/measures/__init__.py
cr/cube/measures/pairwise_significance.py
cr/cube/stripe/__init__.py
cr/cube/stripe/assembler.py
cr/cube/stripe/cubemeasure.py
cr/cube/stripe/insertion.py
cr/cube/stripe/measure.py
cr_cube-3.1.5.dist-info/LICENSE
cr_cube-3.1.5.dist-info/METADATA
cr_cube-3.1.5.dist-info/WHEEL
cr_cube-3.1.5.dist-info/namespace_packages.txt
cr_cube-3.1.5.dist-info/top_level.txt
cr_cube-3.1.5.dist-info/zip-safe
cr_cube-3.1.5.dist-info/RECORD
