Metadata-Version: 2.1
Name: cr-cube
Version: 3.1.5
Summary: Crunch.io Cube library
Home-page: https://github.com/Crunch-io/crunch-cube/
Author: Crunch.io
Author-email: dev@crunch.io
License: MIT License
Classifier: Programming Language :: Python
Classifier: Topic :: Software Development :: Libraries :: Python Modules
License-File: LICENSE
Requires-Dist: scipy
Requires-Dist: tabulate
Provides-Extra: testing
Requires-Dist: pytest; extra == "testing"
Requires-Dist: pytest-cov; extra == "testing"
Requires-Dist: mock; extra == "testing"
Requires-Dist: coverage; extra == "testing"
